{"id":67699845,"node_id":"MDEwOlJlcG9zaXRvcnk2NzY5OTg0NQ==","name":"hello-node","full_name":"gutenye/hello-node","private":false,"owner":{"login":"gutenye","id":377544,"node_id":"MDQ6VXNlcjM3NzU0NA==","avatar_url":"https://avatars.githubusercontent.com/u/377544?v=4","gravatar_id":"","url":"https://api.github.com/users/gutenye","html_url":"https://github.com/gutenye","followers_url":"https://api.github.com/users/gutenye/followers","following_url":"https://api.github.com/users/gutenye/following{/other_user}","gists_url":"https://api.github.com/users/gutenye/gists{/gist_id}","starred_url":"https://api.github.com/users/gutenye/starred{/owner}{/repo}","subscriptions_url":"https://api.github.com/users/gutenye/subscriptions","organizations_url":"https://api.github.com/users/gutenye/orgs","repos_url":"https://api.github.com/users/gutenye/repos","events_url":"https://api.github.com/users/gutenye/events{/privacy}","received_events_url":"https://api.github.com/users/gutenye/received_events","type":"User","site_admin":false},"html_url":"https://github.com/gutenye/hello-node","description":null,"fork":false,"url":"https://api.github.com/repos/gutenye/hello-node","forks_url":"https://api.github.com/repos/gutenye/hello-node/forks","keys_url":"https://api.github.com/repos/gutenye/hello-node/keys{/key_id}","collaborators_url":"https://api.github.com/repos/gutenye/hello-node/collaborators{/collaborator}","teams_url":"https://api.github.com/repos/gutenye/hello-node/teams","hooks_url":"https://api.github.com/repos/gutenye/hello-node/hooks","issue_events_url":"https://api.github.com/repos/gutenye/hello-node/issues/events{/number}","events_url":"https://api.github.com/repos/gutenye/hello-node/events","assignees_url":"https://api.github.com/repos/gutenye/hello-node/assignees{/user}","branches_url":"https://api.github.com/repos/gutenye/hello-node/branches{/branch}","tags_url":"https://api.github.com/repos/gutenye/hello-node/tags","blobs_url":"https://api.github.com/repos/gutenye/hello-node/git/blobs{/sha}","git_tags_url":"https://api.github.com/repos/gutenye/hello-node/git/tags{/sha}","git_refs_url":"https://api.github.com/repos/gutenye/hello-node/git/refs{/sha}","trees_url":"https://api.github.com/repos/gutenye/hello-node/git/trees{/sha}","statuses_url":"https://api.github.com/repos/gutenye/hello-node/statuses/{sha}","languages_url":"https://api.github.com/repos/gutenye/hello-node/languages","stargazers_url":"https://api.github.com/repos/gutenye/hello-node/stargazers","contributors_url":"https://api.github.com/repos/gutenye/hello-node/contributors","subscribers_url":"https://api.github.com/repos/gutenye/hello-node/subscribers","subscription_url":"https://api.github.com/repos/gutenye/hello-node/subscription","commits_url":"https://api.github.com/repos/gutenye/hello-node/commits{/sha}","git_commits_url":"https://api.github.com/repos/gutenye/hello-node/git/commits{/sha}","comments_url":"https://api.github.com/repos/gutenye/hello-node/comments{/number}","issue_comment_url":"https://api.github.com/repos/gutenye/hello-node/issues/comments{/number}","contents_url":"https://api.github.com/repos/gutenye/hello-node/contents/{+path}","compare_url":"https://api.github.com/repos/gutenye/hello-node/compare/{base}...{head}","merges_url":"https://api.github.com/repos/gutenye/hello-node/merges","archive_url":"https://api.github.com/repos/gutenye/hello-node/{archive_format}{/ref}","downloads_url":"https://api.github.com/repos/gutenye/hello-node/downloads","issues_url":"https://api.github.com/repos/gutenye/hello-node/issues{/number}","pulls_url":"https://api.github.com/repos/gutenye/hello-node/pulls{/number}","milestones_url":"https://api.github.com/repos/gutenye/hello-node/milestones{/number}","notifications_url":"https://api.github.com/repos/gutenye/hello-node/notifications{?since,all,participating}","labels_url":"https://api.github.com/repos/gutenye/hello-node/labels{/name}","releases_url":"https://api.github.com/repos/gutenye/hello-node/releases{/id}","deployments_url":"https://api.github.com/repos/gutenye/hello-node/deployments","created_at":"2016-09-08T12:09:37Z","updated_at":"2016-09-08T12:11:28Z","pushed_at":"2016-10-26T03:48:24Z","git_url":"git://github.com/gutenye/hello-node.git","ssh_url":"git@github.com:gutenye/hello-node.git","clone_url":"https://github.com/gutenye/hello-node.git","svn_url":"https://github.com/gutenye/hello-node","homepage":null,"size":35,"stargazers_count":0,"watchers_count":0,"language":"JavaScript","has_issues":true,"has_projects":true,"has_downloads":true,"has_wiki":true,"has_pages":false,"forks_count":0,"mirror_url":null,"archived":false,"disabled":false,"open_issues_count":0,"license":null,"allow_forking":true,"is_template":false,"topics":[],"visibility":"public","forks":0,"open_issues":0,"watchers":0,"default_branch":"master","permissions":{"admin":false,"maintain":false,"push":false,"triage":false,"pull":true},"temp_clone_token":"","network_count":0,"subscribers_count":1}