[{"sha":"7733922d8b82cd2f8a689c82f0a8242c2cb9889c","node_id":"MDY6Q29tbWl0NzkwNTcyNDI6NzczMzkyMmQ4YjgyY2QyZjhhNjg5YzgyZjBhODI0MmMyY2I5ODg5Yw==","commit":{"author":{"name":"Andre Parmeggiani","email":"aaparmeggiani@gmail.com","date":"2020-09-13T19:58:09Z"},"committer":{"name":"Andre Parmeggiani","email":"aaparmeggiani@gmail.com","date":"2020-09-13T19:58:09Z"},"message":"init","tree":{"sha":"538b168a5035a7937f63b1066f8bc499529dc45a","url":"https://api.github.com/repos/aaparmeggiani/towerbridge/git/trees/538b168a5035a7937f63b1066f8bc499529dc45a"},"url":"https://api.github.com/repos/aaparmeggiani/towerbridge/git/commits/7733922d8b82cd2f8a689c82f0a8242c2cb9889c","comment_count":0,"verification":{"verified":false,"reason":"unsigned","signature":null,"payload":null}},"url":"https://api.github.com/repos/aaparmeggiani/towerbridge/commits/7733922d8b82cd2f8a689c82f0a8242c2cb9889c","html_url":"https://github.com/aaparmeggiani/towerbridge/commit/7733922d8b82cd2f8a689c82f0a8242c2cb9889c","comments_url":"https://api.github.com/repos/aaparmeggiani/towerbridge/commits/7733922d8b82cd2f8a689c82f0a8242c2cb9889c/comments","author":{"login":"aaparmeggiani","id":6909,"node_id":"MDQ6VXNlcjY5MDk=","avatar_url":"https://avatars.githubusercontent.com/u/6909?v=4","gravatar_id":"","url":"https://api.github.com/users/aaparmeggiani","html_url":"https://github.com/aaparmeggiani","followers_url":"https://api.github.com/users/aaparmeggiani/followers","following_url":"https://api.github.com/users/aaparmeggiani/following{/other_user}","gists_url":"https://api.github.com/users/aaparmeggiani/gists{/gist_id}","starred_url":"https://api.github.com/users/aaparmeggiani/starred{/owner}{/repo}","subscriptions_url":"https://api.github.com/users/aaparmeggiani/subscriptions","organizations_url":"https://api.github.com/users/aaparmeggiani/orgs","repos_url":"https://api.github.com/users/aaparmeggiani/repos","events_url":"https://api.github.com/users/aaparmeggiani/events{/privacy}","received_events_url":"https://api.github.com/users/aaparmeggiani/received_events","type":"User","site_admin":false},"committer":{"login":"aaparmeggiani","id":6909,"node_id":"MDQ6VXNlcjY5MDk=","avatar_url":"https://avatars.githubusercontent.com/u/6909?v=4","gravatar_id":"","url":"https://api.github.com/users/aaparmeggiani","html_url":"https://github.com/aaparmeggiani","followers_url":"https://api.github.com/users/aaparmeggiani/followers","following_url":"https://api.github.com/users/aaparmeggiani/following{/other_user}","gists_url":"https://api.github.com/users/aaparmeggiani/gists{/gist_id}","starred_url":"https://api.github.com/users/aaparmeggiani/starred{/owner}{/repo}","subscriptions_url":"https://api.github.com/users/aaparmeggiani/subscriptions","organizations_url":"https://api.github.com/users/aaparmeggiani/orgs","repos_url":"https://api.github.com/users/aaparmeggiani/repos","events_url":"https://api.github.com/users/aaparmeggiani/events{/privacy}","received_events_url":"https://api.github.com/users/aaparmeggiani/received_events","type":"User","site_admin":false},"parents":[]}]