[{"login":"erwinvaneyk","id":2803726,"node_id":"MDQ6VXNlcjI4MDM3MjY=","avatar_url":"https://avatars.githubusercontent.com/u/2803726?v=4","gravatar_id":"","url":"https://api.github.com/users/erwinvaneyk","html_url":"https://github.com/erwinvaneyk","followers_url":"https://api.github.com/users/erwinvaneyk/followers","following_url":"https://api.github.com/users/erwinvaneyk/following{/other_user}","gists_url":"https://api.github.com/users/erwinvaneyk/gists{/gist_id}","starred_url":"https://api.github.com/users/erwinvaneyk/starred{/owner}{/repo}","subscriptions_url":"https://api.github.com/users/erwinvaneyk/subscriptions","organizations_url":"https://api.github.com/users/erwinvaneyk/orgs","repos_url":"https://api.github.com/users/erwinvaneyk/repos","events_url":"https://api.github.com/users/erwinvaneyk/events{/privacy}","received_events_url":"https://api.github.com/users/erwinvaneyk/received_events","type":"User","site_admin":false,"contributions":9},{"login":"trensen","id":3601548,"node_id":"MDQ6VXNlcjM2MDE1NDg=","avatar_url":"https://avatars.githubusercontent.com/u/3601548?v=4","gravatar_id":"","url":"https://api.github.com/users/trensen","html_url":"https://github.com/trensen","followers_url":"https://api.github.com/users/trensen/followers","following_url":"https://api.github.com/users/trensen/following{/other_user}","gists_url":"https://api.github.com/users/trensen/gists{/gist_id}","starred_url":"https://api.github.com/users/trensen/starred{/owner}{/repo}","subscriptions_url":"https://api.github.com/users/trensen/subscriptions","organizations_url":"https://api.github.com/users/trensen/orgs","repos_url":"https://api.github.com/users/trensen/repos","events_url":"https://api.github.com/users/trensen/events{/privacy}","received_events_url":"https://api.github.com/users/trensen/received_events","type":"User","site_admin":false,"contributions":2}]