{"id":73993445,"node_id":"MDEwOlJlcG9zaXRvcnk3Mzk5MzQ0NQ==","name":"whatsmyip","full_name":"mdevey/whatsmyip","private":false,"owner":{"login":"mdevey","id":393988,"node_id":"MDQ6VXNlcjM5Mzk4OA==","avatar_url":"https://avatars.githubusercontent.com/u/393988?v=4","gravatar_id":"","url":"https://api.github.com/users/mdevey","html_url":"https://github.com/mdevey","followers_url":"https://api.github.com/users/mdevey/followers","following_url":"https://api.github.com/users/mdevey/following{/other_user}","gists_url":"https://api.github.com/users/mdevey/gists{/gist_id}","starred_url":"https://api.github.com/users/mdevey/starred{/owner}{/repo}","subscriptions_url":"https://api.github.com/users/mdevey/subscriptions","organizations_url":"https://api.github.com/users/mdevey/orgs","repos_url":"https://api.github.com/users/mdevey/repos","events_url":"https://api.github.com/users/mdevey/events{/privacy}","received_events_url":"https://api.github.com/users/mdevey/received_events","type":"User","site_admin":false},"html_url":"https://github.com/mdevey/whatsmyip","description":"Simple \"what's my ip?\" server.  Static golang intended for alpine.","fork":false,"url":"https://api.github.com/repos/mdevey/whatsmyip","forks_url":"https://api.github.com/repos/mdevey/whatsmyip/forks","keys_url":"https://api.github.com/repos/mdevey/whatsmyip/keys{/key_id}","collaborators_url":"https://api.github.com/repos/mdevey/whatsmyip/collaborators{/collaborator}","teams_url":"https://api.github.com/repos/mdevey/whatsmyip/teams","hooks_url":"https://api.github.com/repos/mdevey/whatsmyip/hooks","issue_events_url":"https://api.github.com/repos/mdevey/whatsmyip/issues/events{/number}","events_url":"https://api.github.com/repos/mdevey/whatsmyip/events","assignees_url":"https://api.github.com/repos/mdevey/whatsmyip/assignees{/user}","branches_url":"https://api.github.com/repos/mdevey/whatsmyip/branches{/branch}","tags_url":"https://api.github.com/repos/mdevey/whatsmyip/tags","blobs_url":"https://api.github.com/repos/mdevey/whatsmyip/git/blobs{/sha}","git_tags_url":"https://api.github.com/repos/mdevey/whatsmyip/git/tags{/sha}","git_refs_url":"https://api.github.com/repos/mdevey/whatsmyip/git/refs{/sha}","trees_url":"https://api.github.com/repos/mdevey/whatsmyip/git/trees{/sha}","statuses_url":"https://api.github.com/repos/mdevey/whatsmyip/statuses/{sha}","languages_url":"https://api.github.com/repos/mdevey/whatsmyip/languages","stargazers_url":"https://api.github.com/repos/mdevey/whatsmyip/stargazers","contributors_url":"https://api.github.com/repos/mdevey/whatsmyip/contributors","subscribers_url":"https://api.github.com/repos/mdevey/whatsmyip/subscribers","subscription_url":"https://api.github.com/repos/mdevey/whatsmyip/subscription","commits_url":"https://api.github.com/repos/mdevey/whatsmyip/commits{/sha}","git_commits_url":"https://api.github.com/repos/mdevey/whatsmyip/git/commits{/sha}","comments_url":"https://api.github.com/repos/mdevey/whatsmyip/comments{/number}","issue_comment_url":"https://api.github.com/repos/mdevey/whatsmyip/issues/comments{/number}","contents_url":"https://api.github.com/repos/mdevey/whatsmyip/contents/{+path}","compare_url":"https://api.github.com/repos/mdevey/whatsmyip/compare/{base}...{head}","merges_url":"https://api.github.com/repos/mdevey/whatsmyip/merges","archive_url":"https://api.github.com/repos/mdevey/whatsmyip/{archive_format}{/ref}","downloads_url":"https://api.github.com/repos/mdevey/whatsmyip/downloads","issues_url":"https://api.github.com/repos/mdevey/whatsmyip/issues{/number}","pulls_url":"https://api.github.com/repos/mdevey/whatsmyip/pulls{/number}","milestones_url":"https://api.github.com/repos/mdevey/whatsmyip/milestones{/number}","notifications_url":"https://api.github.com/repos/mdevey/whatsmyip/notifications{?since,all,participating}","labels_url":"https://api.github.com/repos/mdevey/whatsmyip/labels{/name}","releases_url":"https://api.github.com/repos/mdevey/whatsmyip/releases{/id}","deployments_url":"https://api.github.com/repos/mdevey/whatsmyip/deployments","created_at":"2016-11-17T05:28:00Z","updated_at":"2021-01-08T14:11:26Z","pushed_at":"2016-11-24T00:27:26Z","git_url":"git://github.com/mdevey/whatsmyip.git","ssh_url":"git@github.com:mdevey/whatsmyip.git","clone_url":"https://github.com/mdevey/whatsmyip.git","svn_url":"https://github.com/mdevey/whatsmyip","homepage":null,"size":2890,"stargazers_count":1,"watchers_count":1,"language":"Go","has_issues":true,"has_projects":true,"has_downloads":true,"has_wiki":true,"has_pages":false,"forks_count":3,"mirror_url":null,"archived":false,"disabled":false,"open_issues_count":0,"license":null,"allow_forking":true,"is_template":false,"topics":[],"visibility":"public","forks":3,"open_issues":0,"watchers":1,"default_branch":"master","permissions":{"admin":false,"maintain":false,"push":false,"triage":false,"pull":true},"temp_clone_token":"","network_count":3,"subscribers_count":3}