{"id":370615870,"node_id":"MDEwOlJlcG9zaXRvcnkzNzA2MTU4NzA=","name":"web3.py","full_name":"rizalgowandy/web3.py","private":false,"owner":{"login":"rizalgowandy","id":6873609,"node_id":"MDQ6VXNlcjY4NzM2MDk=","avatar_url":"https://avatars.githubusercontent.com/u/6873609?v=4","gravatar_id":"","url":"https://api.github.com/users/rizalgowandy","html_url":"https://github.com/rizalgowandy","followers_url":"https://api.github.com/users/rizalgowandy/followers","following_url":"https://api.github.com/users/rizalgowandy/following{/other_user}","gists_url":"https://api.github.com/users/rizalgowandy/gists{/gist_id}","starred_url":"https://api.github.com/users/rizalgowandy/starred{/owner}{/repo}","subscriptions_url":"https://api.github.com/users/rizalgowandy/subscriptions","organizations_url":"https://api.github.com/users/rizalgowandy/orgs","repos_url":"https://api.github.com/users/rizalgowandy/repos","events_url":"https://api.github.com/users/rizalgowandy/events{/privacy}","received_events_url":"https://api.github.com/users/rizalgowandy/received_events","type":"User","site_admin":false},"html_url":"https://github.com/rizalgowandy/web3.py","description":"A python interface for interacting with the Ethereum blockchain and ecosystem.","fork":true,"url":"https://api.github.com/repos/rizalgowandy/web3.py","forks_url":"https://api.github.com/repos/rizalgowandy/web3.py/forks","keys_url":"https://api.github.com/repos/rizalgowandy/web3.py/keys{/key_id}","collaborators_url":"https://api.github.com/repos/rizalgowandy/web3.py/collaborators{/collaborator}","teams_url":"https://api.github.com/repos/rizalgowandy/web3.py/teams","hooks_url":"https://api.github.com/repos/rizalgowandy/web3.py/hooks","issue_events_url":"https://api.github.com/repos/rizalgowandy/web3.py/issues/events{/number}","events_url":"https://api.github.com/repos/rizalgowandy/web3.py/events","assignees_url":"https://api.github.com/repos/rizalgowandy/web3.py/assignees{/user}","branches_url":"https://api.github.com/repos/rizalgowandy/web3.py/branches{/branch}","tags_url":"https://api.github.com/repos/rizalgowandy/web3.py/tags","blobs_url":"https://api.github.com/repos/rizalgowandy/web3.py/git/blobs{/sha}","git_tags_url":"https://api.github.com/repos/rizalgowandy/web3.py/git/tags{/sha}","git_refs_url":"https://api.github.com/repos/rizalgowandy/web3.py/git/refs{/sha}","trees_url":"https://api.github.com/repos/rizalgowandy/web3.py/git/trees{/sha}","statuses_url":"https://api.github.com/repos/rizalgowandy/web3.py/statuses/{sha}","languages_url":"https://api.github.com/repos/rizalgowandy/web3.py/languages","stargazers_url":"https://api.github.com/repos/rizalgowandy/web3.py/stargazers","contributors_url":"https://api.github.com/repos/rizalgowandy/web3.py/contributors","subscribers_url":"https://api.github.com/repos/rizalgowandy/web3.py/subscribers","subscription_url":"https://api.github.com/repos/rizalgowandy/web3.py/subscription","commits_url":"https://api.github.com/repos/rizalgowandy/web3.py/commits{/sha}","git_commits_url":"https://api.github.com/repos/rizalgowandy/web3.py/git/commits{/sha}","comments_url":"https://api.github.com/repos/rizalgowandy/web3.py/comments{/number}","issue_comment_url":"https://api.github.com/repos/rizalgowandy/web3.py/issues/comments{/number}","contents_url":"https://api.github.com/repos/rizalgowandy/web3.py/contents/{+path}","compare_url":"https://api.github.com/repos/rizalgowandy/web3.py/compare/{base}...{head}","merges_url":"https://api.github.com/repos/rizalgowandy/web3.py/merges","archive_url":"https://api.github.com/repos/rizalgowandy/web3.py/{archive_format}{/ref}","downloads_url":"https://api.github.com/repos/rizalgowandy/web3.py/downloads","issues_url":"https://api.github.com/repos/rizalgowandy/web3.py/issues{/number}","pulls_url":"https://api.github.com/repos/rizalgowandy/web3.py/pulls{/number}","milestones_url":"https://api.github.com/repos/rizalgowandy/web3.py/milestones{/number}","notifications_url":"https://api.github.com/repos/rizalgowandy/web3.py/notifications{?since,all,participating}","labels_url":"https://api.github.com/repos/rizalgowandy/web3.py/labels{/name}","releases_url":"https://api.github.com/repos/rizalgowandy/web3.py/releases{/id}","deployments_url":"https://api.github.com/repos/rizalgowandy/web3.py/deployments","created_at":"2021-05-25T08:14:08Z","updated_at":"2021-11-11T20:33:10Z","pushed_at":"2021-11-11T20:33:06Z","git_url":"git://github.com/rizalgowandy/web3.py.git","ssh_url":"git@github.com:rizalgowandy/web3.py.git","clone_url":"https://github.com/rizalgowandy/web3.py.git","svn_url":"https://github.com/rizalgowandy/web3.py","homepage":"http://web3py.readthedocs.io","size":23493,"stargazers_count":0,"watchers_count":0,"language":"Python","has_issues":false,"has_projects":true,"has_downloads":true,"has_wiki":false,"has_pages":false,"forks_count":0,"mirror_url":null,"archived":false,"disabled":false,"open_issues_count":0,"license":{"key":"mit","name":"MIT License","spdx_id":"MIT","url":"https://api.github.com/licenses/mit","node_id":"MDc6TGljZW5zZTEz"},"allow_forking":true,"is_template":false,"topics":[],"visibility":"public","forks":0,"open_issues":0,"watchers":0,"default_branch":"master","permissions":{"admin":false,"maintain":false,"push":false,"triage":false,"pull":true},"temp_clone_token":"","parent":{"id":56251096,"node_id":"MDEwOlJlcG9zaXRvcnk1NjI1MTA5Ng==","name":"web3.py","full_name":"ethereum/web3.py","private":false,"owner":{"login":"ethereum","id":6250754,"node_id":"MDEyOk9yZ2FuaXphdGlvbjYyNTA3NTQ=","avatar_url":"https://avatars.githubusercontent.com/u/6250754?v=4","gravatar_id":"","url":"https://api.github.com/users/ethereum","html_url":"https://github.com/ethereum","followers_url":"https://api.github.com/users/ethereum/followers","following_url":"https://api.github.com/users/ethereum/following{/other_user}","gists_url":"https://api.github.com/users/ethereum/gists{/gist_id}","starred_url":"https://api.github.com/users/ethereum/starred{/owner}{/repo}","subscriptions_url":"https://api.github.com/users/ethereum/subscriptions","organizations_url":"https://api.github.com/users/ethereum/orgs","repos_url":"https://api.github.com/users/ethereum/repos","events_url":"https://api.github.com/users/ethereum/events{/privacy}","received_events_url":"https://api.github.com/users/ethereum/received_events","type":"Organization","site_admin":false},"html_url":"https://github.com/ethereum/web3.py","description":"A python interface for interacting with the Ethereum blockchain and ecosystem.","fork":false,"url":"https://api.github.com/repos/ethereum/web3.py","forks_url":"https://api.github.com/repos/ethereum/web3.py/forks","keys_url":"https://api.github.com/repos/ethereum/web3.py/keys{/key_id}","collaborators_url":"https://api.github.com/repos/ethereum/web3.py/collaborators{/collaborator}","teams_url":"https://api.github.com/repos/ethereum/web3.py/teams","hooks_url":"https://api.github.com/repos/ethereum/web3.py/hooks","issue_events_url":"https://api.github.com/repos/ethereum/web3.py/issues/events{/number}","events_url":"https://api.github.com/repos/ethereum/web3.py/events","assignees_url":"https://api.github.com/repos/ethereum/web3.py/assignees{/user}","branches_url":"https://api.github.com/repos/ethereum/web3.py/branches{/branch}","tags_url":"https://api.github.com/repos/ethereum/web3.py/tags","blobs_url":"https://api.github.com/repos/ethereum/web3.py/git/blobs{/sha}","git_tags_url":"https://api.github.com/repos/ethereum/web3.py/git/tags{/sha}","git_refs_url":"https://api.github.com/repos/ethereum/web3.py/git/refs{/sha}","trees_url":"https://api.github.com/repos/ethereum/web3.py/git/trees{/sha}","statuses_url":"https://api.github.com/repos/ethereum/web3.py/statuses/{sha}","languages_url":"https://api.github.com/repos/ethereum/web3.py/languages","stargazers_url":"https://api.github.com/repos/ethereum/web3.py/stargazers","contributors_url":"https://api.github.com/repos/ethereum/web3.py/contributors","subscribers_url":"https://api.github.com/repos/ethereum/web3.py/subscribers","subscription_url":"https://api.github.com/repos/ethereum/web3.py/subscription","commits_url":"https://api.github.com/repos/ethereum/web3.py/commits{/sha}","git_commits_url":"https://api.github.com/repos/ethereum/web3.py/git/commits{/sha}","comments_url":"https://api.github.com/repos/ethereum/web3.py/comments{/number}","issue_comment_url":"https://api.github.com/repos/ethereum/web3.py/issues/comments{/number}","contents_url":"https://api.github.com/repos/ethereum/web3.py/contents/{+path}","compare_url":"https://api.github.com/repos/ethereum/web3.py/compare/{base}...{head}","merges_url":"https://api.github.com/repos/ethereum/web3.py/merges","archive_url":"https://api.github.com/repos/ethereum/web3.py/{archive_format}{/ref}","downloads_url":"https://api.github.com/repos/ethereum/web3.py/downloads","issues_url":"https://api.github.com/repos/ethereum/web3.py/issues{/number}","pulls_url":"https://api.github.com/repos/ethereum/web3.py/pulls{/number}","milestones_url":"https://api.github.com/repos/ethereum/web3.py/milestones{/number}","notifications_url":"https://api.github.com/repos/ethereum/web3.py/notifications{?since,all,participating}","labels_url":"https://api.github.com/repos/ethereum/web3.py/labels{/name}","releases_url":"https://api.github.com/repos/ethereum/web3.py/releases{/id}","deployments_url":"https://api.github.com/repos/ethereum/web3.py/deployments","created_at":"2016-04-14T15:59:35Z","updated_at":"2021-11-13T23:51:57Z","pushed_at":"2021-11-13T17:25:57Z","git_url":"git://github.com/ethereum/web3.py.git","ssh_url":"git@github.com:ethereum/web3.py.git","clone_url":"https://github.com/ethereum/web3.py.git","svn_url":"https://github.com/ethereum/web3.py","homepage":"http://web3py.readthedocs.io","size":23467,"stargazers_count":2479,"watchers_count":2479,"language":"Python","has_issues":true,"has_projects":true,"has_downloads":true,"has_wiki":false,"has_pages":false,"forks_count":845,"mirror_url":null,"archived":false,"disabled":false,"open_issues_count":237,"license":{"key":"mit","name":"MIT License","spdx_id":"MIT","url":"https://api.github.com/licenses/mit","node_id":"MDc6TGljZW5zZTEz"},"allow_forking":true,"is_template":false,"topics":[],"visibility":"public","forks":845,"open_issues":237,"watchers":2479,"default_branch":"master"},"source":{"id":56251096,"node_id":"MDEwOlJlcG9zaXRvcnk1NjI1MTA5Ng==","name":"web3.py","full_name":"ethereum/web3.py","private":false,"owner":{"login":"ethereum","id":6250754,"node_id":"MDEyOk9yZ2FuaXphdGlvbjYyNTA3NTQ=","avatar_url":"https://avatars.githubusercontent.com/u/6250754?v=4","gravatar_id":"","url":"https://api.github.com/users/ethereum","html_url":"https://github.com/ethereum","followers_url":"https://api.github.com/users/ethereum/followers","following_url":"https://api.github.com/users/ethereum/following{/other_user}","gists_url":"https://api.github.com/users/ethereum/gists{/gist_id}","starred_url":"https://api.github.com/users/ethereum/starred{/owner}{/repo}","subscriptions_url":"https://api.github.com/users/ethereum/subscriptions","organizations_url":"https://api.github.com/users/ethereum/orgs","repos_url":"https://api.github.com/users/ethereum/repos","events_url":"https://api.github.com/users/ethereum/events{/privacy}","received_events_url":"https://api.github.com/users/ethereum/received_events","type":"Organization","site_admin":false},"html_url":"https://github.com/ethereum/web3.py","description":"A python interface for interacting with the Ethereum blockchain and ecosystem.","fork":false,"url":"https://api.github.com/repos/ethereum/web3.py","forks_url":"https://api.github.com/repos/ethereum/web3.py/forks","keys_url":"https://api.github.com/repos/ethereum/web3.py/keys{/key_id}","collaborators_url":"https://api.github.com/repos/ethereum/web3.py/collaborators{/collaborator}","teams_url":"https://api.github.com/repos/ethereum/web3.py/teams","hooks_url":"https://api.github.com/repos/ethereum/web3.py/hooks","issue_events_url":"https://api.github.com/repos/ethereum/web3.py/issues/events{/number}","events_url":"https://api.github.com/repos/ethereum/web3.py/events","assignees_url":"https://api.github.com/repos/ethereum/web3.py/assignees{/user}","branches_url":"https://api.github.com/repos/ethereum/web3.py/branches{/branch}","tags_url":"https://api.github.com/repos/ethereum/web3.py/tags","blobs_url":"https://api.github.com/repos/ethereum/web3.py/git/blobs{/sha}","git_tags_url":"https://api.github.com/repos/ethereum/web3.py/git/tags{/sha}","git_refs_url":"https://api.github.com/repos/ethereum/web3.py/git/refs{/sha}","trees_url":"https://api.github.com/repos/ethereum/web3.py/git/trees{/sha}","statuses_url":"https://api.github.com/repos/ethereum/web3.py/statuses/{sha}","languages_url":"https://api.github.com/repos/ethereum/web3.py/languages","stargazers_url":"https://api.github.com/repos/ethereum/web3.py/stargazers","contributors_url":"https://api.github.com/repos/ethereum/web3.py/contributors","subscribers_url":"https://api.github.com/repos/ethereum/web3.py/subscribers","subscription_url":"https://api.github.com/repos/ethereum/web3.py/subscription","commits_url":"https://api.github.com/repos/ethereum/web3.py/commits{/sha}","git_commits_url":"https://api.github.com/repos/ethereum/web3.py/git/commits{/sha}","comments_url":"https://api.github.com/repos/ethereum/web3.py/comments{/number}","issue_comment_url":"https://api.github.com/repos/ethereum/web3.py/issues/comments{/number}","contents_url":"https://api.github.com/repos/ethereum/web3.py/contents/{+path}","compare_url":"https://api.github.com/repos/ethereum/web3.py/compare/{base}...{head}","merges_url":"https://api.github.com/repos/ethereum/web3.py/merges","archive_url":"https://api.github.com/repos/ethereum/web3.py/{archive_format}{/ref}","downloads_url":"https://api.github.com/repos/ethereum/web3.py/downloads","issues_url":"https://api.github.com/repos/ethereum/web3.py/issues{/number}","pulls_url":"https://api.github.com/repos/ethereum/web3.py/pulls{/number}","milestones_url":"https://api.github.com/repos/ethereum/web3.py/milestones{/number}","notifications_url":"https://api.github.com/repos/ethereum/web3.py/notifications{?since,all,participating}","labels_url":"https://api.github.com/repos/ethereum/web3.py/labels{/name}","releases_url":"https://api.github.com/repos/ethereum/web3.py/releases{/id}","deployments_url":"https://api.github.com/repos/ethereum/web3.py/deployments","created_at":"2016-04-14T15:59:35Z","updated_at":"2021-11-13T23:51:57Z","pushed_at":"2021-11-13T17:25:57Z","git_url":"git://github.com/ethereum/web3.py.git","ssh_url":"git@github.com:ethereum/web3.py.git","clone_url":"https://github.com/ethereum/web3.py.git","svn_url":"https://github.com/ethereum/web3.py","homepage":"http://web3py.readthedocs.io","size":23467,"stargazers_count":2479,"watchers_count":2479,"language":"Python","has_issues":true,"has_projects":true,"has_downloads":true,"has_wiki":false,"has_pages":false,"forks_count":845,"mirror_url":null,"archived":false,"disabled":false,"open_issues_count":237,"license":{"key":"mit","name":"MIT License","spdx_id":"MIT","url":"https://api.github.com/licenses/mit","node_id":"MDc6TGljZW5zZTEz"},"allow_forking":true,"is_template":false,"topics":[],"visibility":"public","forks":845,"open_issues":237,"watchers":2479,"default_branch":"master"},"network_count":845,"subscribers_count":0}