[{"sha":"a8db8aad83d84b7fec0808cb9970351ef9e34d2a","node_id":"MDY6Q29tbWl0OTM1NjM2MTY6YThkYjhhYWQ4M2Q4NGI3ZmVjMDgwOGNiOTk3MDM1MWVmOWUzNGQyYQ==","commit":{"author":{"name":"Jon Borgonia","email":"jon@gomagames.com","date":"2017-06-13T04:36:08Z"},"committer":{"name":"Jon Borgonia","email":"jon@gomagames.com","date":"2017-06-13T04:36:08Z"},"message":"build ui into public/\n\n- rename static/ public/","tree":{"sha":"81cdb662691acc837784c6db54efda54dc5869f2","url":"https://api.github.com/repos/theRemix/Nineties-Namer/git/trees/81cdb662691acc837784c6db54efda54dc5869f2"},"url":"https://api.github.com/repos/theRemix/Nineties-Namer/git/commits/a8db8aad83d84b7fec0808cb9970351ef9e34d2a","comment_count":0,"verification":{"verified":false,"reason":"unsigned","signature":null,"payload":null}},"url":"https://api.github.com/repos/theRemix/Nineties-Namer/commits/a8db8aad83d84b7fec0808cb9970351ef9e34d2a","html_url":"https://github.com/theRemix/Nineties-Namer/commit/a8db8aad83d84b7fec0808cb9970351ef9e34d2a","comments_url":"https://api.github.com/repos/theRemix/Nineties-Namer/commits/a8db8aad83d84b7fec0808cb9970351ef9e34d2a/comments","author":{"login":"theRemix","id":132562,"node_id":"MDQ6VXNlcjEzMjU2Mg==","avatar_url":"https://avatars.githubusercontent.com/u/132562?v=4","gravatar_id":"","url":"https://api.github.com/users/theRemix","html_url":"https://github.com/theRemix","followers_url":"https://api.github.com/users/theRemix/followers","following_url":"https://api.github.com/users/theRemix/following{/other_user}","gists_url":"https://api.github.com/users/theRemix/gists{/gist_id}","starred_url":"https://api.github.com/users/theRemix/starred{/owner}{/repo}","subscriptions_url":"https://api.github.com/users/theRemix/subscriptions","organizations_url":"https://api.github.com/users/theRemix/orgs","repos_url":"https://api.github.com/users/theRemix/repos","events_url":"https://api.github.com/users/theRemix/events{/privacy}","received_events_url":"https://api.github.com/users/theRemix/received_events","type":"User","site_admin":false},"committer":{"login":"theRemix","id":132562,"node_id":"MDQ6VXNlcjEzMjU2Mg==","avatar_url":"https://avatars.githubusercontent.com/u/132562?v=4","gravatar_id":"","url":"https://api.github.com/users/theRemix","html_url":"https://github.com/theRemix","followers_url":"https://api.github.com/users/theRemix/followers","following_url":"https://api.github.com/users/theRemix/following{/other_user}","gists_url":"https://api.github.com/users/theRemix/gists{/gist_id}","starred_url":"https://api.github.com/users/theRemix/starred{/owner}{/repo}","subscriptions_url":"https://api.github.com/users/theRemix/subscriptions","organizations_url":"https://api.github.com/users/theRemix/orgs","repos_url":"https://api.github.com/users/theRemix/repos","events_url":"https://api.github.com/users/theRemix/events{/privacy}","received_events_url":"https://api.github.com/users/theRemix/received_events","type":"User","site_admin":false},"parents":[{"sha":"109cf206324300a08c5b37145111adab215cf312","url":"https://api.github.com/repos/theRemix/Nineties-Namer/commits/109cf206324300a08c5b37145111adab215cf312","html_url":"https://github.com/theRemix/Nineties-Namer/commit/109cf206324300a08c5b37145111adab215cf312"}]}]