[{"sha":"8be3ef4e3435cfe5aca277367669b320b91c7be6","node_id":"MDY6Q29tbWl0MzIyNDc4NDc6OGJlM2VmNGUzNDM1Y2ZlNWFjYTI3NzM2NzY2OWIzMjBiOTFjN2JlNg==","commit":{"author":{"name":"Hermel","email":"edenh13@gmail.com","date":"2019-11-30T21:03:24Z"},"committer":{"name":"Jan-Niklas W","email":"6104311+JWO719@users.noreply.github.com","date":"2019-11-30T21:03:24Z"},"message":"docs (Docker support for docs_app) (#4719)\n\n* added Docker support for docs_app.\r\nadded 2 new files:\r\n* added .dockerignore - for ignoring node_modules, logs, etc.\r\n* Dockerfile - installing the docs app and exposing port for use.\r\nupdated 2 existing files:\r\n* package.json - start script is running the stable version + host flag\r\n* readme - updated with the docker commands\r\n\r\n* docs(docs_app): adding docker support for docs app\r\n\r\nadded `start:docker` script  to package.json (instead of modifying the original start script)\r\nDockerfile CMD is start:docker now\r\nthe README.md is updated to instruct how to save the container for offline support\r\n\r\n* changed node version to LTS for better stability","tree":{"sha":"7e7b84619acce8482e6a76e9dc9caa549fdd8839","url":"https://api.github.com/repos/ReactiveX/rxjs/git/trees/7e7b84619acce8482e6a76e9dc9caa549fdd8839"},"url":"https://api.github.com/repos/ReactiveX/rxjs/git/commits/8be3ef4e3435cfe5aca277367669b320b91c7be6","comment_count":1,"verification":{"verified":false,"reason":"unsigned","signature":null,"payload":null}},"url":"https://api.github.com/repos/ReactiveX/rxjs/commits/8be3ef4e3435cfe5aca277367669b320b91c7be6","html_url":"https://github.com/ReactiveX/rxjs/commit/8be3ef4e3435cfe5aca277367669b320b91c7be6","comments_url":"https://api.github.com/repos/ReactiveX/rxjs/commits/8be3ef4e3435cfe5aca277367669b320b91c7be6/comments","author":{"login":"edenhermelin","id":10133343,"node_id":"MDQ6VXNlcjEwMTMzMzQz","avatar_url":"https://avatars.githubusercontent.com/u/10133343?v=4","gravatar_id":"","url":"https://api.github.com/users/edenhermelin","html_url":"https://github.com/edenhermelin","followers_url":"https://api.github.com/users/edenhermelin/followers","following_url":"https://api.github.com/users/edenhermelin/following{/other_user}","gists_url":"https://api.github.com/users/edenhermelin/gists{/gist_id}","starred_url":"https://api.github.com/users/edenhermelin/starred{/owner}{/repo}","subscriptions_url":"https://api.github.com/users/edenhermelin/subscriptions","organizations_url":"https://api.github.com/users/edenhermelin/orgs","repos_url":"https://api.github.com/users/edenhermelin/repos","events_url":"https://api.github.com/users/edenhermelin/events{/privacy}","received_events_url":"https://api.github.com/users/edenhermelin/received_events","type":"User","site_admin":false},"committer":{"login":"niklas-wortmann","id":6104311,"node_id":"MDQ6VXNlcjYxMDQzMTE=","avatar_url":"https://avatars.githubusercontent.com/u/6104311?v=4","gravatar_id":"","url":"https://api.github.com/users/niklas-wortmann","html_url":"https://github.com/niklas-wortmann","followers_url":"https://api.github.com/users/niklas-wortmann/followers","following_url":"https://api.github.com/users/niklas-wortmann/following{/other_user}","gists_url":"https://api.github.com/users/niklas-wortmann/gists{/gist_id}","starred_url":"https://api.github.com/users/niklas-wortmann/starred{/owner}{/repo}","subscriptions_url":"https://api.github.com/users/niklas-wortmann/subscriptions","organizations_url":"https://api.github.com/users/niklas-wortmann/orgs","repos_url":"https://api.github.com/users/niklas-wortmann/repos","events_url":"https://api.github.com/users/niklas-wortmann/events{/privacy}","received_events_url":"https://api.github.com/users/niklas-wortmann/received_events","type":"User","site_admin":false},"parents":[{"sha":"267b4a4e61c7973787ed6d8b7f449aa7a91b923a","url":"https://api.github.com/repos/ReactiveX/rxjs/commits/267b4a4e61c7973787ed6d8b7f449aa7a91b923a","html_url":"https://github.com/ReactiveX/rxjs/commit/267b4a4e61c7973787ed6d8b7f449aa7a91b923a"}]}]