[{"sha":"f966c77eeebd421f596ac92606c29f3b630c8c78","node_id":"MDY6Q29tbWl0NTM4MDY4MTE6Zjk2NmM3N2VlZWJkNDIxZjU5NmFjOTI2MDZjMjlmM2I2MzBjOGM3OA==","commit":{"author":{"name":"Vincent Behar","email":"v.behar@free.fr","date":"2016-03-13T20:44:55Z"},"committer":{"name":"Vincent Behar","email":"v.behar@free.fr","date":"2016-03-13T20:44:55Z"},"message":"initial commit","tree":{"sha":"6409bcb7df9ebc538ffb299a25cafdd496c2d40f","url":"https://api.github.com/repos/vbehar/openshift-flowdock-notifier/git/trees/6409bcb7df9ebc538ffb299a25cafdd496c2d40f"},"url":"https://api.github.com/repos/vbehar/openshift-flowdock-notifier/git/commits/f966c77eeebd421f596ac92606c29f3b630c8c78","comment_count":0,"verification":{"verified":false,"reason":"unsigned","signature":null,"payload":null}},"url":"https://api.github.com/repos/vbehar/openshift-flowdock-notifier/commits/f966c77eeebd421f596ac92606c29f3b630c8c78","html_url":"https://github.com/vbehar/openshift-flowdock-notifier/commit/f966c77eeebd421f596ac92606c29f3b630c8c78","comments_url":"https://api.github.com/repos/vbehar/openshift-flowdock-notifier/commits/f966c77eeebd421f596ac92606c29f3b630c8c78/comments","author":{"login":"vbehar","id":6251,"node_id":"MDQ6VXNlcjYyNTE=","avatar_url":"https://avatars.githubusercontent.com/u/6251?v=4","gravatar_id":"","url":"https://api.github.com/users/vbehar","html_url":"https://github.com/vbehar","followers_url":"https://api.github.com/users/vbehar/followers","following_url":"https://api.github.com/users/vbehar/following{/other_user}","gists_url":"https://api.github.com/users/vbehar/gists{/gist_id}","starred_url":"https://api.github.com/users/vbehar/starred{/owner}{/repo}","subscriptions_url":"https://api.github.com/users/vbehar/subscriptions","organizations_url":"https://api.github.com/users/vbehar/orgs","repos_url":"https://api.github.com/users/vbehar/repos","events_url":"https://api.github.com/users/vbehar/events{/privacy}","received_events_url":"https://api.github.com/users/vbehar/received_events","type":"User","site_admin":false},"committer":{"login":"vbehar","id":6251,"node_id":"MDQ6VXNlcjYyNTE=","avatar_url":"https://avatars.githubusercontent.com/u/6251?v=4","gravatar_id":"","url":"https://api.github.com/users/vbehar","html_url":"https://github.com/vbehar","followers_url":"https://api.github.com/users/vbehar/followers","following_url":"https://api.github.com/users/vbehar/following{/other_user}","gists_url":"https://api.github.com/users/vbehar/gists{/gist_id}","starred_url":"https://api.github.com/users/vbehar/starred{/owner}{/repo}","subscriptions_url":"https://api.github.com/users/vbehar/subscriptions","organizations_url":"https://api.github.com/users/vbehar/orgs","repos_url":"https://api.github.com/users/vbehar/repos","events_url":"https://api.github.com/users/vbehar/events{/privacy}","received_events_url":"https://api.github.com/users/vbehar/received_events","type":"User","site_admin":false},"parents":[]}]