[{"login":"cpoppema","id":1432901,"node_id":"MDQ6VXNlcjE0MzI5MDE=","avatar_url":"https://avatars.githubusercontent.com/u/1432901?v=4","gravatar_id":"","url":"https://api.github.com/users/cpoppema","html_url":"https://github.com/cpoppema","followers_url":"https://api.github.com/users/cpoppema/followers","following_url":"https://api.github.com/users/cpoppema/following{/other_user}","gists_url":"https://api.github.com/users/cpoppema/gists{/gist_id}","starred_url":"https://api.github.com/users/cpoppema/starred{/owner}{/repo}","subscriptions_url":"https://api.github.com/users/cpoppema/subscriptions","organizations_url":"https://api.github.com/users/cpoppema/orgs","repos_url":"https://api.github.com/users/cpoppema/repos","events_url":"https://api.github.com/users/cpoppema/events{/privacy}","received_events_url":"https://api.github.com/users/cpoppema/received_events","type":"User","site_admin":false,"contributions":6},{"login":"staxmanade","id":156715,"node_id":"MDQ6VXNlcjE1NjcxNQ==","avatar_url":"https://avatars.githubusercontent.com/u/156715?v=4","gravatar_id":"","url":"https://api.github.com/users/staxmanade","html_url":"https://github.com/staxmanade","followers_url":"https://api.github.com/users/staxmanade/followers","following_url":"https://api.github.com/users/staxmanade/following{/other_user}","gists_url":"https://api.github.com/users/staxmanade/gists{/gist_id}","starred_url":"https://api.github.com/users/staxmanade/starred{/owner}{/repo}","subscriptions_url":"https://api.github.com/users/staxmanade/subscriptions","organizations_url":"https://api.github.com/users/staxmanade/orgs","repos_url":"https://api.github.com/users/staxmanade/repos","events_url":"https://api.github.com/users/staxmanade/events{/privacy}","received_events_url":"https://api.github.com/users/staxmanade/received_events","type":"User","site_admin":false,"contributions":2}]