[{"login":"shoonoise","id":2296996,"node_id":"MDQ6VXNlcjIyOTY5OTY=","avatar_url":"https://avatars.githubusercontent.com/u/2296996?v=4","gravatar_id":"","url":"https://api.github.com/users/shoonoise","html_url":"https://github.com/shoonoise","followers_url":"https://api.github.com/users/shoonoise/followers","following_url":"https://api.github.com/users/shoonoise/following{/other_user}","gists_url":"https://api.github.com/users/shoonoise/gists{/gist_id}","starred_url":"https://api.github.com/users/shoonoise/starred{/owner}{/repo}","subscriptions_url":"https://api.github.com/users/shoonoise/subscriptions","organizations_url":"https://api.github.com/users/shoonoise/orgs","repos_url":"https://api.github.com/users/shoonoise/repos","events_url":"https://api.github.com/users/shoonoise/events{/privacy}","received_events_url":"https://api.github.com/users/shoonoise/received_events","type":"User","site_admin":false,"contributions":83}]