[{"login":"Enkhtuvshin0513","id":37796969,"node_id":"MDQ6VXNlcjM3Nzk2OTY5","avatar_url":"https://avatars.githubusercontent.com/u/37796969?v=4","gravatar_id":"","url":"https://api.github.com/users/Enkhtuvshin0513","html_url":"https://github.com/Enkhtuvshin0513","followers_url":"https://api.github.com/users/Enkhtuvshin0513/followers","following_url":"https://api.github.com/users/Enkhtuvshin0513/following{/other_user}","gists_url":"https://api.github.com/users/Enkhtuvshin0513/gists{/gist_id}","starred_url":"https://api.github.com/users/Enkhtuvshin0513/starred{/owner}{/repo}","subscriptions_url":"https://api.github.com/users/Enkhtuvshin0513/subscriptions","organizations_url":"https://api.github.com/users/Enkhtuvshin0513/orgs","repos_url":"https://api.github.com/users/Enkhtuvshin0513/repos","events_url":"https://api.github.com/users/Enkhtuvshin0513/events{/privacy}","received_events_url":"https://api.github.com/users/Enkhtuvshin0513/received_events","type":"User","site_admin":false,"contributions":16},{"login":"nandirb","id":58172661,"node_id":"MDQ6VXNlcjU4MTcyNjYx","avatar_url":"https://avatars.githubusercontent.com/u/58172661?v=4","gravatar_id":"","url":"https://api.github.com/users/nandirb","html_url":"https://github.com/nandirb","followers_url":"https://api.github.com/users/nandirb/followers","following_url":"https://api.github.com/users/nandirb/following{/other_user}","gists_url":"https://api.github.com/users/nandirb/gists{/gist_id}","starred_url":"https://api.github.com/users/nandirb/starred{/owner}{/repo}","subscriptions_url":"https://api.github.com/users/nandirb/subscriptions","organizations_url":"https://api.github.com/users/nandirb/orgs","repos_url":"https://api.github.com/users/nandirb/repos","events_url":"https://api.github.com/users/nandirb/events{/privacy}","received_events_url":"https://api.github.com/users/nandirb/received_events","type":"User","site_admin":false,"contributions":14},{"login":"Anu-Ujin","id":23444147,"node_id":"MDQ6VXNlcjIzNDQ0MTQ3","avatar_url":"https://avatars.githubusercontent.com/u/23444147?v=4","gravatar_id":"","url":"https://api.github.com/users/Anu-Ujin","html_url":"https://github.com/Anu-Ujin","followers_url":"https://api.github.com/users/Anu-Ujin/followers","following_url":"https://api.github.com/users/Anu-Ujin/following{/other_user}","gists_url":"https://api.github.com/users/Anu-Ujin/gists{/gist_id}","starred_url":"https://api.github.com/users/Anu-Ujin/starred{/owner}{/repo}","subscriptions_url":"https://api.github.com/users/Anu-Ujin/subscriptions","organizations_url":"https://api.github.com/users/Anu-Ujin/orgs","repos_url":"https://api.github.com/users/Anu-Ujin/repos","events_url":"https://api.github.com/users/Anu-Ujin/events{/privacy}","received_events_url":"https://api.github.com/users/Anu-Ujin/received_events","type":"User","site_admin":false,"contributions":14},{"login":"Jason-2020","id":58852063,"node_id":"MDQ6VXNlcjU4ODUyMDYz","avatar_url":"https://avatars.githubusercontent.com/u/58852063?v=4","gravatar_id":"","url":"https://api.github.com/users/Jason-2020","html_url":"https://github.com/Jason-2020","followers_url":"https://api.github.com/users/Jason-2020/followers","following_url":"https://api.github.com/users/Jason-2020/following{/other_user}","gists_url":"https://api.github.com/users/Jason-2020/gists{/gist_id}","starred_url":"https://api.github.com/users/Jason-2020/starred{/owner}{/repo}","subscriptions_url":"https://api.github.com/users/Jason-2020/subscriptions","organizations_url":"https://api.github.com/users/Jason-2020/orgs","repos_url":"https://api.github.com/users/Jason-2020/repos","events_url":"https://api.github.com/users/Jason-2020/events{/privacy}","received_events_url":"https://api.github.com/users/Jason-2020/received_events","type":"User","site_admin":false,"contributions":12},{"login":"Mambatukaa","id":56122037,"node_id":"MDQ6VXNlcjU2MTIyMDM3","avatar_url":"https://avatars.githubusercontent.com/u/56122037?v=4","gravatar_id":"","url":"https://api.github.com/users/Mambatukaa","html_url":"https://github.com/Mambatukaa","followers_url":"https://api.github.com/users/Mambatukaa/followers","following_url":"https://api.github.com/users/Mambatukaa/following{/other_user}","gists_url":"https://api.github.com/users/Mambatukaa/gists{/gist_id}","starred_url":"https://api.github.com/users/Mambatukaa/starred{/owner}{/repo}","subscriptions_url":"https://api.github.com/users/Mambatukaa/subscriptions","organizations_url":"https://api.github.com/users/Mambatukaa/orgs","repos_url":"https://api.github.com/users/Mambatukaa/repos","events_url":"https://api.github.com/users/Mambatukaa/events{/privacy}","received_events_url":"https://api.github.com/users/Mambatukaa/received_events","type":"User","site_admin":false,"contributions":9},{"login":"munkhorgil","id":978987,"node_id":"MDQ6VXNlcjk3ODk4Nw==","avatar_url":"https://avatars.githubusercontent.com/u/978987?v=4","gravatar_id":"","url":"https://api.github.com/users/munkhorgil","html_url":"https://github.com/munkhorgil","followers_url":"https://api.github.com/users/munkhorgil/followers","following_url":"https://api.github.com/users/munkhorgil/following{/other_user}","gists_url":"https://api.github.com/users/munkhorgil/gists{/gist_id}","starred_url":"https://api.github.com/users/munkhorgil/starred{/owner}{/repo}","subscriptions_url":"https://api.github.com/users/munkhorgil/subscriptions","organizations_url":"https://api.github.com/users/munkhorgil/orgs","repos_url":"https://api.github.com/users/munkhorgil/repos","events_url":"https://api.github.com/users/munkhorgil/events{/privacy}","received_events_url":"https://api.github.com/users/munkhorgil/received_events","type":"User","site_admin":false,"contributions":3},{"login":"uuganaa1333","id":26920801,"node_id":"MDQ6VXNlcjI2OTIwODAx","avatar_url":"https://avatars.githubusercontent.com/u/26920801?v=4","gravatar_id":"","url":"https://api.github.com/users/uuganaa1333","html_url":"https://github.com/uuganaa1333","followers_url":"https://api.github.com/users/uuganaa1333/followers","following_url":"https://api.github.com/users/uuganaa1333/following{/other_user}","gists_url":"https://api.github.com/users/uuganaa1333/gists{/gist_id}","starred_url":"https://api.github.com/users/uuganaa1333/starred{/owner}{/repo}","subscriptions_url":"https://api.github.com/users/uuganaa1333/subscriptions","organizations_url":"https://api.github.com/users/uuganaa1333/orgs","repos_url":"https://api.github.com/users/uuganaa1333/repos","events_url":"https://api.github.com/users/uuganaa1333/events{/privacy}","received_events_url":"https://api.github.com/users/uuganaa1333/received_events","type":"User","site_admin":false,"contributions":2}]