[{"login":"mbilokonsky","id":603525,"node_id":"MDQ6VXNlcjYwMzUyNQ==","avatar_url":"https://avatars.githubusercontent.com/u/603525?v=4","gravatar_id":"","url":"https://api.github.com/users/mbilokonsky","html_url":"https://github.com/mbilokonsky","followers_url":"https://api.github.com/users/mbilokonsky/followers","following_url":"https://api.github.com/users/mbilokonsky/following{/other_user}","gists_url":"https://api.github.com/users/mbilokonsky/gists{/gist_id}","starred_url":"https://api.github.com/users/mbilokonsky/starred{/owner}{/repo}","subscriptions_url":"https://api.github.com/users/mbilokonsky/subscriptions","organizations_url":"https://api.github.com/users/mbilokonsky/orgs","repos_url":"https://api.github.com/users/mbilokonsky/repos","events_url":"https://api.github.com/users/mbilokonsky/events{/privacy}","received_events_url":"https://api.github.com/users/mbilokonsky/received_events","type":"User","site_admin":false,"contributions":36},{"login":"rtucker","id":97437,"node_id":"MDQ6VXNlcjk3NDM3","avatar_url":"https://avatars.githubusercontent.com/u/97437?v=4","gravatar_id":"","url":"https://api.github.com/users/rtucker","html_url":"https://github.com/rtucker","followers_url":"https://api.github.com/users/rtucker/followers","following_url":"https://api.github.com/users/rtucker/following{/other_user}","gists_url":"https://api.github.com/users/rtucker/gists{/gist_id}","starred_url":"https://api.github.com/users/rtucker/starred{/owner}{/repo}","subscriptions_url":"https://api.github.com/users/rtucker/subscriptions","organizations_url":"https://api.github.com/users/rtucker/orgs","repos_url":"https://api.github.com/users/rtucker/repos","events_url":"https://api.github.com/users/rtucker/events{/privacy}","received_events_url":"https://api.github.com/users/rtucker/received_events","type":"User","site_admin":false,"contributions":27},{"login":"KellerFuchs","id":14331571,"node_id":"MDQ6VXNlcjE0MzMxNTcx","avatar_url":"https://avatars.githubusercontent.com/u/14331571?v=4","gravatar_id":"","url":"https://api.github.com/users/KellerFuchs","html_url":"https://github.com/KellerFuchs","followers_url":"https://api.github.com/users/KellerFuchs/followers","following_url":"https://api.github.com/users/KellerFuchs/following{/other_user}","gists_url":"https://api.github.com/users/KellerFuchs/gists{/gist_id}","starred_url":"https://api.github.com/users/KellerFuchs/starred{/owner}{/repo}","subscriptions_url":"https://api.github.com/users/KellerFuchs/subscriptions","organizations_url":"https://api.github.com/users/KellerFuchs/orgs","repos_url":"https://api.github.com/users/KellerFuchs/repos","events_url":"https://api.github.com/users/KellerFuchs/events{/privacy}","received_events_url":"https://api.github.com/users/KellerFuchs/received_events","type":"User","site_admin":false,"contributions":4}]