[{"sha":"b1270e249a4ebf8c79a7c560ecffb6f5086ee02b","node_id":"MDY6Q29tbWl0NjQzOTA2MTI6YjEyNzBlMjQ5YTRlYmY4Yzc5YTdjNTYwZWNmZmI2ZjUwODZlZTAyYg==","commit":{"author":{"name":"Alexander Tishchenko","email":"atishch@gmail.com","date":"2021-06-09T12:31:53Z"},"committer":{"name":"Petr Gotthard","email":"petr.gotthard@centrum.cz","date":"2021-06-09T14:51:13Z"},"message":"Bug in Dockerfile. We must specify OTP 21 explicitly, run fails with newer OTP.","tree":{"sha":"eacc80e76e1baeb71e7655a7b003fb00ee5927e1","url":"https://api.github.com/repos/gotthardp/lorawan-server/git/trees/eacc80e76e1baeb71e7655a7b003fb00ee5927e1"},"url":"https://api.github.com/repos/gotthardp/lorawan-server/git/commits/b1270e249a4ebf8c79a7c560ecffb6f5086ee02b","comment_count":0,"verification":{"verified":false,"reason":"unsigned","signature":null,"payload":null}},"url":"https://api.github.com/repos/gotthardp/lorawan-server/commits/b1270e249a4ebf8c79a7c560ecffb6f5086ee02b","html_url":"https://github.com/gotthardp/lorawan-server/commit/b1270e249a4ebf8c79a7c560ecffb6f5086ee02b","comments_url":"https://api.github.com/repos/gotthardp/lorawan-server/commits/b1270e249a4ebf8c79a7c560ecffb6f5086ee02b/comments","author":{"login":"altishchenko","id":19464159,"node_id":"MDQ6VXNlcjE5NDY0MTU5","avatar_url":"https://avatars.githubusercontent.com/u/19464159?v=4","gravatar_id":"","url":"https://api.github.com/users/altishchenko","html_url":"https://github.com/altishchenko","followers_url":"https://api.github.com/users/altishchenko/followers","following_url":"https://api.github.com/users/altishchenko/following{/other_user}","gists_url":"https://api.github.com/users/altishchenko/gists{/gist_id}","starred_url":"https://api.github.com/users/altishchenko/starred{/owner}{/repo}","subscriptions_url":"https://api.github.com/users/altishchenko/subscriptions","organizations_url":"https://api.github.com/users/altishchenko/orgs","repos_url":"https://api.github.com/users/altishchenko/repos","events_url":"https://api.github.com/users/altishchenko/events{/privacy}","received_events_url":"https://api.github.com/users/altishchenko/received_events","type":"User","site_admin":false},"committer":{"login":"gotthardp","id":939979,"node_id":"MDQ6VXNlcjkzOTk3OQ==","avatar_url":"https://avatars.githubusercontent.com/u/939979?v=4","gravatar_id":"","url":"https://api.github.com/users/gotthardp","html_url":"https://github.com/gotthardp","followers_url":"https://api.github.com/users/gotthardp/followers","following_url":"https://api.github.com/users/gotthardp/following{/other_user}","gists_url":"https://api.github.com/users/gotthardp/gists{/gist_id}","starred_url":"https://api.github.com/users/gotthardp/starred{/owner}{/repo}","subscriptions_url":"https://api.github.com/users/gotthardp/subscriptions","organizations_url":"https://api.github.com/users/gotthardp/orgs","repos_url":"https://api.github.com/users/gotthardp/repos","events_url":"https://api.github.com/users/gotthardp/events{/privacy}","received_events_url":"https://api.github.com/users/gotthardp/received_events","type":"User","site_admin":false},"parents":[{"sha":"13b1409b57e079499a633bca20a33eb5acdf05ee","url":"https://api.github.com/repos/gotthardp/lorawan-server/commits/13b1409b57e079499a633bca20a33eb5acdf05ee","html_url":"https://github.com/gotthardp/lorawan-server/commit/13b1409b57e079499a633bca20a33eb5acdf05ee"}]}]