[{"sha":"b6b8bcfcd2adaddba98d62938410a38c947db204","node_id":"MDY6Q29tbWl0Njk1OTQ5NTI6YjZiOGJjZmNkMmFkYWRkYmE5OGQ2MjkzODQxMGEzOGM5NDdkYjIwNA==","commit":{"author":{"name":"bonanza123","email":"bonanza123@users.noreply.github.com","date":"2016-09-30T15:54:23Z"},"committer":{"name":"GitHub","email":"noreply@github.com","date":"2016-09-30T15:54:23Z"},"message":"Update Dockerfile","tree":{"sha":"2dfc83d9f7f4f37d607d742c4c0e6db837b400a5","url":"https://api.github.com/repos/bonanza123/matlab-support/git/trees/2dfc83d9f7f4f37d607d742c4c0e6db837b400a5"},"url":"https://api.github.com/repos/bonanza123/matlab-support/git/commits/b6b8bcfcd2adaddba98d62938410a38c947db204","comment_count":0,"verification":{"verified":false,"reason":"unsigned","signature":null,"payload":null}},"url":"https://api.github.com/repos/bonanza123/matlab-support/commits/b6b8bcfcd2adaddba98d62938410a38c947db204","html_url":"https://github.com/bonanza123/matlab-support/commit/b6b8bcfcd2adaddba98d62938410a38c947db204","comments_url":"https://api.github.com/repos/bonanza123/matlab-support/commits/b6b8bcfcd2adaddba98d62938410a38c947db204/comments","author":{"login":"bonanza123","id":3331227,"node_id":"MDQ6VXNlcjMzMzEyMjc=","avatar_url":"https://avatars.githubusercontent.com/u/3331227?v=4","gravatar_id":"","url":"https://api.github.com/users/bonanza123","html_url":"https://github.com/bonanza123","followers_url":"https://api.github.com/users/bonanza123/followers","following_url":"https://api.github.com/users/bonanza123/following{/other_user}","gists_url":"https://api.github.com/users/bonanza123/gists{/gist_id}","starred_url":"https://api.github.com/users/bonanza123/starred{/owner}{/repo}","subscriptions_url":"https://api.github.com/users/bonanza123/subscriptions","organizations_url":"https://api.github.com/users/bonanza123/orgs","repos_url":"https://api.github.com/users/bonanza123/repos","events_url":"https://api.github.com/users/bonanza123/events{/privacy}","received_events_url":"https://api.github.com/users/bonanza123/received_events","type":"User","site_admin":false},"committer":{"login":"web-flow","id":19864447,"node_id":"MDQ6VXNlcjE5ODY0NDQ3","avatar_url":"https://avatars.githubusercontent.com/u/19864447?v=4","gravatar_id":"","url":"https://api.github.com/users/web-flow","html_url":"https://github.com/web-flow","followers_url":"https://api.github.com/users/web-flow/followers","following_url":"https://api.github.com/users/web-flow/following{/other_user}","gists_url":"https://api.github.com/users/web-flow/gists{/gist_id}","starred_url":"https://api.github.com/users/web-flow/starred{/owner}{/repo}","subscriptions_url":"https://api.github.com/users/web-flow/subscriptions","organizations_url":"https://api.github.com/users/web-flow/orgs","repos_url":"https://api.github.com/users/web-flow/repos","events_url":"https://api.github.com/users/web-flow/events{/privacy}","received_events_url":"https://api.github.com/users/web-flow/received_events","type":"User","site_admin":false},"parents":[{"sha":"1f62b0efb530499a1333c491362b8e0d6a6f90dd","url":"https://api.github.com/repos/bonanza123/matlab-support/commits/1f62b0efb530499a1333c491362b8e0d6a6f90dd","html_url":"https://github.com/bonanza123/matlab-support/commit/1f62b0efb530499a1333c491362b8e0d6a6f90dd"}]}]