[{"sha":"ed187d83b7ae7f83fa3d7874d8b06ec07121ecf2","node_id":"MDY6Q29tbWl0Nzg3MzA0ODc6ZWQxODdkODNiN2FlN2Y4M2ZhM2Q3ODc0ZDhiMDZlYzA3MTIxZWNmMg==","commit":{"author":{"name":"Peter Novotnak","email":"peter.novotnak@reddit.com","date":"2020-10-07T17:51:18Z"},"committer":{"name":"Peter Novotnak","email":"peter.novotnak@reddit.com","date":"2020-10-07T17:51:18Z"},"message":"use fortio from upstream image","tree":{"sha":"82e556fe65585a169b9bf844d2445d932d359581","url":"https://api.github.com/repos/pnovotnak/it/git/trees/82e556fe65585a169b9bf844d2445d932d359581"},"url":"https://api.github.com/repos/pnovotnak/it/git/commits/ed187d83b7ae7f83fa3d7874d8b06ec07121ecf2","comment_count":0,"verification":{"verified":false,"reason":"unsigned","signature":null,"payload":null}},"url":"https://api.github.com/repos/pnovotnak/it/commits/ed187d83b7ae7f83fa3d7874d8b06ec07121ecf2","html_url":"https://github.com/pnovotnak/it/commit/ed187d83b7ae7f83fa3d7874d8b06ec07121ecf2","comments_url":"https://api.github.com/repos/pnovotnak/it/commits/ed187d83b7ae7f83fa3d7874d8b06ec07121ecf2/comments","author":{"login":"pnovotnak","id":5713245,"node_id":"MDQ6VXNlcjU3MTMyNDU=","avatar_url":"https://avatars.githubusercontent.com/u/5713245?v=4","gravatar_id":"","url":"https://api.github.com/users/pnovotnak","html_url":"https://github.com/pnovotnak","followers_url":"https://api.github.com/users/pnovotnak/followers","following_url":"https://api.github.com/users/pnovotnak/following{/other_user}","gists_url":"https://api.github.com/users/pnovotnak/gists{/gist_id}","starred_url":"https://api.github.com/users/pnovotnak/starred{/owner}{/repo}","subscriptions_url":"https://api.github.com/users/pnovotnak/subscriptions","organizations_url":"https://api.github.com/users/pnovotnak/orgs","repos_url":"https://api.github.com/users/pnovotnak/repos","events_url":"https://api.github.com/users/pnovotnak/events{/privacy}","received_events_url":"https://api.github.com/users/pnovotnak/received_events","type":"User","site_admin":false},"committer":{"login":"pnovotnak","id":5713245,"node_id":"MDQ6VXNlcjU3MTMyNDU=","avatar_url":"https://avatars.githubusercontent.com/u/5713245?v=4","gravatar_id":"","url":"https://api.github.com/users/pnovotnak","html_url":"https://github.com/pnovotnak","followers_url":"https://api.github.com/users/pnovotnak/followers","following_url":"https://api.github.com/users/pnovotnak/following{/other_user}","gists_url":"https://api.github.com/users/pnovotnak/gists{/gist_id}","starred_url":"https://api.github.com/users/pnovotnak/starred{/owner}{/repo}","subscriptions_url":"https://api.github.com/users/pnovotnak/subscriptions","organizations_url":"https://api.github.com/users/pnovotnak/orgs","repos_url":"https://api.github.com/users/pnovotnak/repos","events_url":"https://api.github.com/users/pnovotnak/events{/privacy}","received_events_url":"https://api.github.com/users/pnovotnak/received_events","type":"User","site_admin":false},"parents":[{"sha":"1c3c3b2613a3cd8fd91e343dbd067b24cf7c1cfb","url":"https://api.github.com/repos/pnovotnak/it/commits/1c3c3b2613a3cd8fd91e343dbd067b24cf7c1cfb","html_url":"https://github.com/pnovotnak/it/commit/1c3c3b2613a3cd8fd91e343dbd067b24cf7c1cfb"}]}]